{"architecture-concepts_facades.md":"B2ELYYJ8","architecture-concepts_request-lifecycle.md":"H0HTI_2w","architecture-concepts_service-container.md":"Bns_TQM-","architecture-concepts_service-providers.md":"B9YrW3xv","database_getting-started.md":"Cisqf05d","database_migrations.md":"BSY86NWd","database_queries.md":"CN9e-kMY","database_seeding.md":"DYD7DqZ1","digging-deeper_artisan-console.md":"q99zBNcE","digging-deeper_cache.md":"Cyw51VwY","digging-deeper_color.md":"dcMtEOEG","digging-deeper_event.md":"agND2sVB","digging-deeper_filesystem.md":"e9CD3ylv","digging-deeper_helpers.md":"BYhl33jn","digging-deeper_http-client.md":"ay70sqjx","digging-deeper_localization.md":"E_yM0ns4","digging-deeper_mail.md":"DvjqwLc1","digging-deeper_package-development.md":"CBItsIo-","digging-deeper_pluralization.md":"tQUTdJ7c","digging-deeper_processes.md":"DX5_4Xps","digging-deeper_queues.md":"RJCyloc5","digging-deeper_strings.md":"BMKIdDzJ","digging-deeper_task-scheduling.md":"YpTiYKr0","fr_fr_architecture-concepts_facades.md":"DHey36df","fr_fr_architecture-concepts_request-lifecycle.md":"BWZD0LIA","fr_fr_architecture-concepts_service-container.md":"QoVFpmDd","fr_fr_architecture-concepts_service-providers.md":"CbWywEp6","fr_fr_database_getting-started.md":"DajggHpq","fr_fr_database_migrations.md":"BPSM6USu","fr_fr_database_queries.md":"Zf754N9u","fr_fr_database_seeding.md":"BmYVmeMy","fr_fr_digging-deeper_artisan-console.md":"CDKJ_s9X","fr_fr_digging-deeper_cache.md":"Cb6z9G-R","fr_fr_digging-deeper_color.md":"DbXXvNVY","fr_fr_digging-deeper_event.md":"DXOxBZxu","fr_fr_digging-deeper_filesystem.md":"DhIK2R-q","fr_fr_digging-deeper_helpers.md":"DvCBe4Tb","fr_fr_digging-deeper_http-client.md":"DQjepxPa","fr_fr_digging-deeper_localization.md":"CAM_dd4_","fr_fr_digging-deeper_mail.md":"CSIBoFAI","fr_fr_digging-deeper_package-development.md":"DmfwiwhY","fr_fr_digging-deeper_queues.md":"UziofCd0","fr_fr_digging-deeper_strings.md":"StzQJLBO","fr_fr_digging-deeper_task-scheduling.md":"qK8T-jtY","fr_fr_getting-started_compile.md":"BIFH9GFs","fr_fr_getting-started_configuration.md":"DuykIEjG","fr_fr_getting-started_contributions.md":"BOED3b7g","fr_fr_getting-started_directory-structure.md":"BklCHBt3","fr_fr_getting-started_installation.md":"CKvU1Q5o","fr_fr_getting-started_packages.md":"BPmn5kYy","fr_fr_getting-started_privacy.md":"D_u0agg-","fr_fr_getting-started_releases.md":"DV9dIKFv","fr_fr_index.md":"0XMCreZl","fr_fr_orm_factories.md":"S0-IXsOm","fr_fr_orm_getting-started.md":"CQI86Bv3","fr_fr_orm_relationships.md":"CngfqyC5","fr_fr_readme.md":"BZO1ZhWO","fr_fr_security_authentication.md":"BjHgR_oZ","fr_fr_security_authorization.md":"CctlTp8H","fr_fr_security_encryption.md":"B_9m8QQy","fr_fr_security_hashing.md":"C3cF5EYG","fr_fr_testing_getting-started.md":"PKMaTQ7s","fr_fr_testing_http-tests.md":"CxeTeL1j","fr_fr_testing_mock.md":"D_38n36h","fr_fr_the-basics_controllers.md":"CyDbpXrw","fr_fr_the-basics_grpc.md":"CXT33Yvy","fr_fr_the-basics_logging.md":"DgR-ZogH","fr_fr_the-basics_middleware.md":"C-wKUVCZ","fr_fr_the-basics_request.md":"ByukkeOu","fr_fr_the-basics_response.md":"DORqVwBp","fr_fr_the-basics_routing.md":"BnfY1c_K","fr_fr_the-basics_session.md":"_lLrJdJg","fr_fr_the-basics_validation.md":"Bc2DgIcA","fr_fr_the-basics_views.md":"CLR3kto2","fr_fr_upgrade_history.md":"BiIh7IO4","fr_fr_upgrade_v1.1.md":"BM3zZ7af","fr_fr_upgrade_v1.10.md":"Cq-qbS4i","fr_fr_upgrade_v1.11.md":"CjYAzbPw","fr_fr_upgrade_v1.12.md":"2M8iOMMC","fr_fr_upgrade_v1.13.md":"CDdg6NY1","fr_fr_upgrade_v1.14.md":"CBb3enj4","fr_fr_upgrade_v1.15.md":"CaFWsZWo","fr_fr_upgrade_v1.16.md":"DzE-5FJq","fr_fr_upgrade_v1.2.md":"aOy7mxZd","fr_fr_upgrade_v1.3.md":"Cub58fuK","fr_fr_upgrade_v1.4.md":"CimGvUM4","fr_fr_upgrade_v1.5.md":"qJaDyuig","fr_fr_upgrade_v1.6.md":"JaCzoLH4","fr_fr_upgrade_v1.7.md":"itA9AFqA","fr_fr_upgrade_v1.8.md":"FAf2u9Q3","fr_fr_upgrade_v1.9.md":"Dyg3cP__","getting-started_compile.md":"DRpkXrU_","getting-started_configuration.md":"TuiPbG66","getting-started_directory-structure.md":"Cgfq_OY4","getting-started_installation.md":"Bdriy6xV","getting-started_packages.md":"DlkK_Da2","index.md":"CGR5UlSE","orm_factories.md":"BuxRW8S1","orm_getting-started.md":"Ctr02tnW","orm_relationships.md":"BCTUqipI","prologue_compare-with-laravel.md":"B4pyDtlq","prologue_contributions.md":"ui5ln4z3","prologue_privacy.md":"3OxJFwK0","prologue_releases.md":"DhmKaZjc","readme.md":"CLiEW1Zp","security_authentication.md":"BFeDz2Tv","security_authorization.md":"DcwtsfOe","security_encryption.md":"DFBvkypr","security_hashing.md":"Z4TkNToh","testing_getting-started.md":"CYA_ZppK","testing_http-tests.md":"BZ20oIQT","testing_mock.md":"D05A331W","the-basics_controllers.md":"O_89T-uS","the-basics_grpc.md":"BINgykZS","the-basics_logging.md":"CFeZdK2w","the-basics_middleware.md":"DJZ6GhPI","the-basics_request.md":"C4zVC7ra","the-basics_response.md":"5JDXqf1X","the-basics_routing.md":"BM3lAbC5","the-basics_session.md":"lukvUmva","the-basics_validation.md":"CiUpwrBJ","the-basics_views.md":"ChEZk-v7","upgrade_history.md":"DG5ZCrb4","upgrade_v1.1.md":"oOCoO_af","upgrade_v1.10.md":"BNMAGThd","upgrade_v1.11.md":"DdGqF81-","upgrade_v1.12.md":"DRBbWBIj","upgrade_v1.13.md":"CJrynvyy","upgrade_v1.14.md":"C9EEUEXv","upgrade_v1.15.md":"ZYmSV-0a","upgrade_v1.16.md":"nIxUT7jX","upgrade_v1.17.md":"DXXYq0Sl","upgrade_v1.2.md":"BhIcNNFu","upgrade_v1.3.md":"uAKel0Pa","upgrade_v1.4.md":"B1ZMwbKc","upgrade_v1.5.md":"DpVcBfmz","upgrade_v1.6.md":"DLzNQMrS","upgrade_v1.7.md":"lAeBiu1H","upgrade_v1.8.md":"DJay6BpY","upgrade_v1.9.md":"CrwHCf5l","zh_cn_architecture-concepts_facades.md":"CloyLDw3","zh_cn_architecture-concepts_request-lifecycle.md":"D9lEV3uh","zh_cn_architecture-concepts_service-container.md":"DldB79IS","zh_cn_architecture-concepts_service-providers.md":"CmfdeZ3-","zh_cn_database_getting-started.md":"pH3o1P7X","zh_cn_database_migrations.md":"Doe-0Zpd","zh_cn_database_queries.md":"C-42MITV","zh_cn_database_seeding.md":"DENlyeNK","zh_cn_digging-deeper_artisan-console.md":"XwjmUq3m","zh_cn_digging-deeper_cache.md":"CmXlpXgK","zh_cn_digging-deeper_color.md":"BaB10VsD","zh_cn_digging-deeper_event.md":"BJRg06o3","zh_cn_digging-deeper_filesystem.md":"DgTYmbfR","zh_cn_digging-deeper_helpers.md":"Cv4-6E0F","zh_cn_digging-deeper_http-client.md":"C2viGOWW","zh_cn_digging-deeper_localization.md":"CR0xB18f","zh_cn_digging-deeper_mail.md":"Dc3pE5Fh","zh_cn_digging-deeper_package-development.md":"RSSSHv6K","zh_cn_digging-deeper_queues.md":"Cqeze383","zh_cn_digging-deeper_strings.md":"CV7C-IFC","zh_cn_digging-deeper_task-scheduling.md":"DtgYipE1","zh_cn_getting-started_compile.md":"BjMefQZw","zh_cn_getting-started_configuration.md":"B-q_KDf4","zh_cn_getting-started_contributions.md":"DN82fJ_w","zh_cn_getting-started_directory-structure.md":"r7ex6mN-","zh_cn_getting-started_installation.md":"DmWIUzbm","zh_cn_getting-started_packages.md":"BhuEpBuB","zh_cn_getting-started_privacy.md":"DqVHfzkE","zh_cn_getting-started_releases.md":"CkGgEqfB","zh_cn_index.md":"DcdMcQIr","zh_cn_orm_factories.md":"B7slXoUf","zh_cn_orm_getting-started.md":"Cah59HkO","zh_cn_orm_relationships.md":"DagV4PLk","zh_cn_readme.md":"DXoF51vB","zh_cn_security_authentication.md":"Q_wmUqRK","zh_cn_security_authorization.md":"imWq2S-S","zh_cn_security_encryption.md":"Du9NuTC6","zh_cn_security_hashing.md":"ClJ3V_lL","zh_cn_testing_getting-started.md":"CWerp5gu","zh_cn_testing_http-tests.md":"aFj1udew","zh_cn_testing_mock.md":"BWmfNSiC","zh_cn_the-basics_controllers.md":"Dv6Y_RI7","zh_cn_the-basics_grpc.md":"DuCVlAk8","zh_cn_the-basics_logging.md":"BZsn243T","zh_cn_the-basics_middleware.md":"BZL7ObN_","zh_cn_the-basics_readme.md":"CM3CrIEp","zh_cn_the-basics_request.md":"CcGfPnq-","zh_cn_the-basics_response.md":"Dz4kGp03","zh_cn_the-basics_routing.md":"DyoHBXg0","zh_cn_the-basics_session.md":"BsJWfQLH","zh_cn_the-basics_validation.md":"DVm6v9fn","zh_cn_the-basics_views.md":"B9KxtuE0","zh_cn_upgrade_history.md":"s8r4hcuO","zh_cn_upgrade_v1.1.md":"9lw9927B","zh_cn_upgrade_v1.10.md":"Da1CiMWj","zh_cn_upgrade_v1.11.md":"CF9DyBAt","zh_cn_upgrade_v1.12.md":"D4_k2ztE","zh_cn_upgrade_v1.13.md":"BDExv1nr","zh_cn_upgrade_v1.14.md":"ZWcWUG8_","zh_cn_upgrade_v1.15.md":"Bv_ZRhDd","zh_cn_upgrade_v1.16.md":"NF2B15EF","zh_cn_upgrade_v1.2.md":"DqRbPpRJ","zh_cn_upgrade_v1.3.md":"BOp2JNLM","zh_cn_upgrade_v1.4.md":"D6XNWeDo","zh_cn_upgrade_v1.5.md":"CW1xl1lP","zh_cn_upgrade_v1.6.md":"DZezQn90","zh_cn_upgrade_v1.7.md":"ChprWGLS","zh_cn_upgrade_v1.8.md":"CJ-oFQCy","zh_cn_upgrade_v1.9.md":"bYszcYOx","zh_tw_architecture-concepts_facades.md":"ShtWj0Hh","zh_tw_architecture-concepts_request-lifecycle.md":"DGssVif-","zh_tw_architecture-concepts_service-container.md":"Vei8v_4n","zh_tw_architecture-concepts_service-providers.md":"DLKMVMYH","zh_tw_database_getting-started.md":"Cl_u2RB9","zh_tw_database_migrations.md":"6J-YgZga","zh_tw_database_queries.md":"7NEPAFbR","zh_tw_database_seeding.md":"3aWNYI1B","zh_tw_digging-deeper_artisan-console.md":"yndN7eSc","zh_tw_digging-deeper_cache.md":"BRuiUrGF","zh_tw_digging-deeper_color.md":"B8AybCMA","zh_tw_digging-deeper_event.md":"ChPpm80A","zh_tw_digging-deeper_filesystem.md":"C1I48jSK","zh_tw_digging-deeper_helpers.md":"CepJ9bC8","zh_tw_digging-deeper_http-client.md":"CxChKp4u","zh_tw_digging-deeper_localization.md":"D0E9BQPC","zh_tw_digging-deeper_mail.md":"Bmfoxd7s","zh_tw_digging-deeper_package-development.md":"DzCo9Xxy","zh_tw_digging-deeper_queues.md":"BRwxigpd","zh_tw_digging-deeper_strings.md":"CqAX9NB1","zh_tw_digging-deeper_task-scheduling.md":"L91-vU99","zh_tw_getting-started_compile.md":"j2ixdy1s","zh_tw_getting-started_configuration.md":"C3gJF1jD","zh_tw_getting-started_contributions.md":"B7HMeHI_","zh_tw_getting-started_directory-structure.md":"CevDbn3k","zh_tw_getting-started_installation.md":"BtC1aY-n","zh_tw_getting-started_packages.md":"-M15yvIL","zh_tw_getting-started_privacy.md":"Dv7OJy41","zh_tw_getting-started_releases.md":"Bpc4rvbb","zh_tw_index.md":"BWeXrIK7","zh_tw_orm_factories.md":"C1YU3rbt","zh_tw_orm_getting-started.md":"BoRZ8fP4","zh_tw_orm_relationships.md":"BKpJgTq_","zh_tw_readme.md":"Brg3Mxu5","zh_tw_security_authentication.md":"aBjmUBiM","zh_tw_security_authorization.md":"KDuk1qmp","zh_tw_security_encryption.md":"BFlfCRXZ","zh_tw_security_hashing.md":"DdtOLmkD","zh_tw_testing_getting-started.md":"CcVET59c","zh_tw_testing_http-tests.md":"DZrNKH_f","zh_tw_testing_mock.md":"CogYMFHX","zh_tw_the-basics_controllers.md":"B1JVKH0f","zh_tw_the-basics_grpc.md":"Cwb9B57n","zh_tw_the-basics_logging.md":"jLeSVbLi","zh_tw_the-basics_middleware.md":"B3B2uNAS","zh_tw_the-basics_request.md":"CWTGxxTZ","zh_tw_the-basics_response.md":"B0wAzePd","zh_tw_the-basics_routing.md":"cxEHsDPk","zh_tw_the-basics_session.md":"CCmspAie","zh_tw_the-basics_validation.md":"DhJ-L4Gs","zh_tw_the-basics_views.md":"C10DHOgl","zh_tw_upgrade_history.md":"CGR3lt1_","zh_tw_upgrade_v1.1.md":"D33TDG4Y","zh_tw_upgrade_v1.10.md":"BFrtvZqB","zh_tw_upgrade_v1.11.md":"Yoiw7f-X","zh_tw_upgrade_v1.12.md":"glH_h4pe","zh_tw_upgrade_v1.13.md":"DBbbUrY_","zh_tw_upgrade_v1.14.md":"_raOaYoT","zh_tw_upgrade_v1.15.md":"BEgRrLE0","zh_tw_upgrade_v1.16.md":"CoU8OKuG","zh_tw_upgrade_v1.2.md":"ixPohI3L","zh_tw_upgrade_v1.3.md":"BFqyKkYO","zh_tw_upgrade_v1.4.md":"LtXzkXPB","zh_tw_upgrade_v1.5.md":"BG54KKsv","zh_tw_upgrade_v1.6.md":"C94ov0so","zh_tw_upgrade_v1.7.md":"ljfXuSnr","zh_tw_upgrade_v1.8.md":"CnuXlUGt","zh_tw_upgrade_v1.9.md":"CVXsWVSh"}
